gaga/GA.py
gaga/Individual.py
gaga/Results.py
gaga/__init__.py
gaga-0.1.1.dist-info/METADATA
gaga-0.1.1.dist-info/WHEEL
gaga-0.1.1.dist-info/top_level.txt
gaga-0.1.1.dist-info/RECORD
