Metadata-Version: 2.1
Name: gaga
Version: 0.1.1
Summary: A genetic algorithm
Home-page: https://github.com/awon8465/gaga
Author: Alison Wong
Author-email: a.wong@sydney.edu.au
License: UNKNOWN
Platform: UNKNOWN
Classifier: Development Status :: 4 - Beta
Classifier: Programming Language :: Python :: 3
Requires-Dist: numpy
Requires-Dist: matplotlib
Requires-Dist: bz2file
